AUTHORS.txt
LICENSE.txt
MANIFEST.in
README.rst
setup.py
argyle/__init__.py
argyle/base.py
argyle/nginx.py
argyle/npm.py
argyle/postgres.py
argyle/python.py
argyle/rabbitmq.py
argyle/supervisor.py
argyle/system.py
argyle.egg-info/PKG-INFO
argyle.egg-info/SOURCES.txt
argyle.egg-info/dependency_links.txt
argyle.egg-info/requires.txt
argyle.egg-info/top_level.txt
argyle/templates/nginx/site.conf
argyle/templates/supervisor/base.conf
argyle/templates/supervisor/celery.conf
argyle/templates/supervisor/gunicorn.conf
argyle/tests/__init__.py
argyle/tests/test_base.py
argyle/tests/test_nginx.py
argyle/tests/test_npm.py
argyle/tests/test_postgres.py
argyle/tests/test_rabbitmq.py
argyle/tests/test_supervisor.py
argyle/tests/test_system.py
argyle/tests/utils.py
argyle/tests/data/packages.txt
argyle/tests/data/ppas.txt
argyle/tests/data/sources.txt