Metadata-Version: 1.1
Name: argyle
Version: 0.2.0
Summary: Argyle is a collection of Fabric utilities for Django deployment.
Home-page: https://github.com/mlavin/argyle
Author: Mark Lavin
Author-email: markdlavin@gmail.com
License: BSD
Platform: UNKNOWN
Classifier: Topic :: Internet :: WWW/HTTP :: Dynamic Content
Classifier: Intended Audience :: Developers
Classifier: License :: OSI Approved :: BSD License
Classifier: Programming Language :: Python
Classifier: Programming Language :: Python :: 2.6
Classifier: Programming Language :: Python :: 2.7
Classifier: Topic :: Software Development :: Libraries :: Python Modules
Classifier: Development Status :: 4 - Beta
Classifier: Operating System :: OS Independent
